cparser/__init__.py
geo_dataread/__init__.py
geo_dataread/gas_read.py
geo_dataread/gps_read.py
geo_dataread/hytro_read.py
geofunc/__init__.py
geofunc/geo.py
geofunc/geofunc.py
gpsUtils/gpsUtils.py
gtimes/__init__.py
gtimes/gpstime.py
gtimes/timecalc.py
gtimes/timefunc.py
receivers/__init__.py
receivers/getSeptentrio3.py
gpslibrary-0.2.17.dist-info/LICENSE
gpslibrary-0.2.17.dist-info/METADATA
gpslibrary-0.2.17.dist-info/WHEEL
gpslibrary-0.2.17.dist-info/entry_points.txt
gpslibrary-0.2.17.dist-info/RECORD
