Metadata-Version: 2.1
Name: gpslibrary
Version: 0.2.17
Summary: Library to handle reading, analysing and ploting GPS and other data
Author: Benedikt Gunnar Ófeigsson
Author-email: bgo@vedur.is
Requires-Python: >=3.10,<3.13
Classifier: Programming Language :: Python :: 3
Classifier: Programming Language :: Python :: 3.10
Classifier: Programming Language :: Python :: 3.11
Classifier: Programming Language :: Python :: 3.12
Requires-Dist: icecream (>=2.1.3,<3.0.0)
Requires-Dist: numpy (>=1.24.3,<2.0.0)
Requires-Dist: pandas (>=2.0.1,<3.0.0)
Requires-Dist: psycopg2-binary (>=2.9.6,<3.0.0)
Requires-Dist: pyproj (>=3.5.0,<4.0.0)
Requires-Dist: python-dateutil (>=2.8.2,<3.0.0)
Requires-Dist: pytz (>=2023.3,<2024.0)
Requires-Dist: requests (>=2.31.0,<3.0.0)
Requires-Dist: scipy (>=1.10.1,<2.0.0)
Requires-Dist: sqlalchemy (>=1.4.36,<2.0.0)
